[
    {
        "title": "The Impact of AI on Modern Software Development",
        "author": "John Smith",
        "year": "2024",
        "sourceType": "article",
        "publisher": "Tech Review Quarterly",
        "volume": "15",
        "pages": "45-52",
        "doi": "10.1234/ai.2024.1234"
    },
    {
        "title": "UX Design Principles for the Modern Web",
        "author": "Jane Doe, Robert Wilson",
        "year": "2024",
        "sourceType": "book",
        "publisher": "Web Design Press",
        "edition": "2nd Edition",
        "isbn": "978-0-123456-78-9",
        "doi": "10.1234/book.2024.5678"
    },
    {
        "title": "Agile Development Best Practices",
        "author": "Robert Johnson, Sarah Lee, Michael Chang",
        "year": "2024",
        "sourceType": "conference",
        "publisher": "International Conference on Software Engineering",
        "websiteOrganization": "IEEE",
        "url": "https://example.com/agile-practices",
        "doi": "10.1109/ICSE.2024.1234"
    },
    {
        "title": "The Future of Web Development",
        "author": "Emily Wilson",
        "year": "2024",
        "sourceType": "website",
        "websiteOrganization": "Web Dev Insights",
        "url": "https://example.com/future-web",
        "lastAccessed": "2024-03-15"
    },
    {
        "title": "Marketing in the Digital Age",
        "author": "Michael Brown, Jennifer Smith, David Lee, Anna Chen",
        "year": "2024",
        "sourceType": "report",
        "publisher": "Digital Marketing Institute",
        "reportNumber": "DMI-2024-001",
        "url": "https://example.com/digital-marketing",
        "doi": "10.1234/dmi.2024.001"
    }
]